picozk/__init__.py
picozk/binary_int.py
picozk/compiler.py
picozk/config.py
picozk/datatypes.py
picozk/functions.py
picozk/ram.py
picozk/sha256.py
picozk/util.py
picozk/wire.py
picozk/poseidon_hash/__init__.py
picozk/poseidon_hash/poseidon_hash.py
picozk/poseidon_hash/poseidon_round_constants.py
picozk/poseidon_hash/poseidon_round_numbers.py
picozk-0.4.dist-info/LICENSE
picozk-0.4.dist-info/METADATA
picozk-0.4.dist-info/WHEEL
picozk-0.4.dist-info/top_level.txt
picozk-0.4.dist-info/RECORD
