Metadata-Version: 2.1
Name: picozk
Version: 0.4
Summary: PicoZK library & compiler for writing zero-knowledge statements
Author-email: Joe Near <jnear@uvm.edu>
License: MIT License
Project-URL: Repository, https://github.com/uvm-plaid/picozk
Requires-Python: <=3.11.7,>=3.9
License-File: LICENSE
Provides-Extra: examples
Requires-Dist: ecdsa ==0.18.0 ; extra == 'examples'
Requires-Dist: galois ==0.3.7 ; extra == 'examples'
Requires-Dist: numpy ==1.25.2 ; extra == 'examples'
Requires-Dist: pandas ==2.2.0 ; extra == 'examples'
Requires-Dist: scipy ==1.12.0 ; extra == 'examples'
Requires-Dist: scikit-learn ==1.4.0 ; extra == 'examples'
Requires-Dist: torch ==2.2.0 ; extra == 'examples'
Requires-Dist: torchvision ==0.17.0 ; extra == 'examples'
